{
  "symbol": "GBPUSD",
  "timestamp": "20250616_212027",
  "hyperparameters": {
    "lookback_window": 35,
    "max_features": 30,
    "feature_selection_method": "rfe",
    "scaler_type": "standard",
    "conv1d_filters_1": 24,
    "conv1d_filters_2": 40,
    "conv1d_kernel_size": 2,
    "lstm_units": 95,
    "lstm_return_sequences": false,
    "dense_units": 55,
    "num_dense_layers": 1,
    "dropout_rate": 0.18062399776459812,
    "l1_reg": 6.84161687963078e-06,
    "l2_reg": 0.00013548995815613728,
    "batch_normalization": true,
    "optimizer": "adam",
    "learning_rate": 0.0020048555080136718,
    "batch_size": 96,
    "epochs": 101,
    "patience": 8,
    "reduce_lr_patience": 7,
    "confidence_threshold_high": 0.6096996238554965,
    "confidence_threshold_low": 0.373056890749282,
    "signal_smoothing": false,
    "use_rcs_features": true,
    "use_cross_pair_features": false
  },
  "selected_features": [
    "returns",
    "log_returns",
    "high_low_pct",
    "atr_14",
    "rsi_7",
    "rsi_14",
    "rsi_21",
    "rsi_divergence",
    "rsi_momentum",
    "bbw",
    "bb_position",
    "macd",
    "macd_signal",
    "macd_histogram",
    "sma_slope_10",
    "sma_slope_20",
    "sma_slope_50",
    "rcs_5",
    "rcs_10",
    "rcs_momentum",
    "rcs_acceleration",
    "rcs_divergence",
    "session_us",
    "hour",
    "cci",
    "adx",
    "engulfing",
    "volume",
    "volume_ratio",
    "price_volume"
  ],
  "num_features": 30,
  "lookback_window": 35,
  "input_shape": [
    35,
    30
  ],
  "model_architecture": "CNN-LSTM",
  "framework": "tensorflow/keras",
  "export_format": "ONNX_ONLY",
  "scaler_type": "RobustScaler",
  "onnx_compatible": true,
  "trading_system_compatible": true,
  "feature_mapping": {
    "bb_lower_20_2": "bb_lower",
    "bb_upper_20_2": "bb_upper",
    "bb_middle_20_2": "bb_middle",
    "bb_position_20_2": "bb_position",
    "bb_width_20_2": "bbw",
    "atr_norm_14": "atr_normalized_14",
    "atr_norm_21": "atr_normalized_21",
    "doji_pattern": "doji",
    "hammer_pattern": "hammer",
    "engulfing_pattern": "engulfing",
    "macd_line": "macd",
    "macd_signal_line": "macd_signal",
    "rsi_14_overbought": "rsi_overbought",
    "rsi_14_oversold": "rsi_oversold"
  },
  "legacy_features_included": true,
  "phase_2_correlations_included": true,
  "session_logic_fixed": true,
  "threshold_validation_fixed": true,
  "gradient_clipping_enabled": true
}